ckanext_mailcraft-0.9.3-py3.11-nspkg.pth
ckanext/mailcraft/__init__.py
ckanext/mailcraft/config.py
ckanext/mailcraft/exception.py
ckanext/mailcraft/interfaces.py
ckanext/mailcraft/mailer.py
ckanext/mailcraft/plugin.py
ckanext/mailcraft/types.py
ckanext/mailcraft/utils.py
ckanext/mailcraft/templates/mailcraft/emails/base.html
ckanext/mailcraft/templates/mailcraft/emails/test.html
ckanext/mailcraft/templates/mailcraft/emails/reset_password/body.html
ckanext/mailcraft/tests/__init__.py
ckanext/mailcraft/tests/test_mailer.py
ckanext/mailcraft_dashboard/__init__.py
ckanext/mailcraft_dashboard/formatters.py
ckanext/mailcraft_dashboard/model.py
ckanext/mailcraft_dashboard/plugin.py
ckanext/mailcraft_dashboard/table.py
ckanext/mailcraft_dashboard/views.py
ckanext/mailcraft_dashboard/logic/action.py
ckanext/mailcraft_dashboard/logic/auth.py
ckanext/mailcraft_dashboard/logic/schema.py
ckanext/mailcraft_dashboard/logic/validators.py
ckanext/mailcraft_dashboard/migration/mailcraft_dashboard/env.py
ckanext/mailcraft_dashboard/migration/mailcraft_dashboard/versions/9f83e5bfff72_add_mailcraft_mail_table.py
ckanext/mailcraft_dashboard/tests/__init__.py
ckanext/mailcraft_dashboard/tests/conftest.py
ckanext/mailcraft_dashboard/tests/test_actions.py
ckanext_mailcraft-0.9.3.dist-info/licenses/LICENSE
ckanext_mailcraft-0.9.3.dist-info/METADATA
ckanext_mailcraft-0.9.3.dist-info/WHEEL
ckanext_mailcraft-0.9.3.dist-info/entry_points.txt
ckanext_mailcraft-0.9.3.dist-info/namespace_packages.txt
ckanext_mailcraft-0.9.3.dist-info/top_level.txt
ckanext_mailcraft-0.9.3.dist-info/RECORD
