Metadata-Version: 2.4
Name: ckanext-mailcraft
Version: 0.9.3
Summary: Custom extandable mailer for CKAN
Author-email: DataShades <datashades@linkdigital.com.au>, Oleksandr Cherniavskyi <mutantsan@gmail.com>
Maintainer-email: DataShades <datashades@linkdigital.com.au>
License: GNU AFFERO GENERAL PUBLIC LICENSE
Project-URL: Homepage, https://github.com/DataShades/ckanext-mailcraft
Keywords: CKAN
Classifier: Development Status :: 4 - Beta
Classifier: License :: OSI Approved :: GNU Affero General Public License v3 or later (AGPLv3+)
Classifier: Programming Language :: Python :: 3.8
Classifier: Programming Language :: Python :: 3.9
Classifier: Programming Language :: Python :: 3.10
License-File: LICENSE
Requires-Dist: ckanext-tables<2.0.0,>=1.8.0
Dynamic: license-file
